{"is_source_file": false, "format": "", "description": "", "external_files": [], "external_methods": [], "published": [], "classes": [], "methods": [], "calls": [], "search-terms": ["ticket-booking-app", "README.md"], "state": 2, "file_id": 4, "knowledge_revision": 7, "git_revision": "17d6278821478361a64bf233bcac84322580a29f", "hash": "8468cc32a0df2d6fec3ffd9f5b650c9f", "format-version": 4, "code-base-name": "MobileApp", "filename": "README.md", "revision_history": [{"7": "17d6278821478361a64bf233bcac84322580a29f"}]}